opensoar/__init__.py
opensoar/version.py
opensoar/competition/__init__.py
opensoar/competition/competition_day.py
opensoar/competition/competitor.py
opensoar/competition/crosscountry.py
opensoar/competition/daily_results_page.py
opensoar/competition/soaringspot.py
opensoar/competition/strepla.py
opensoar/task/__init__.py
opensoar/task/aat.py
opensoar/task/race_task.py
opensoar/task/task.py
opensoar/task/trip.py
opensoar/task/waypoint.py
opensoar/thermals/__init__.py
opensoar/thermals/flight_phases.py
opensoar/thermals/pysoar_thermal_detector.py
opensoar/utilities/__init__.py
opensoar/utilities/geojson_serializers.py
opensoar/utilities/helper_functions.py
opensoar/utilities/retry_utils.py
opensoar-2.1.0.dist-info/licenses/LICENSE
opensoar-2.1.0.dist-info/METADATA
opensoar-2.1.0.dist-info/WHEEL
opensoar-2.1.0.dist-info/top_level.txt
opensoar-2.1.0.dist-info/RECORD
