Metadata-Version: 2.4
Name: opensoar
Version: 2.1.0
Summary: Open source python library for glider flight analysis
Home-page: https://github.com/glidergeek/opensoar
License: MIT
License-File: LICENSE
Requires-Dist: aerofiles~=1.4.0
Requires-Dist: beautifulsoup4~=4.6.0
Requires-Dist: pyproj>=3.4.1
Requires-Dist: geojson>=3.0.0
Requires-Dist: shapely>2.0.0
Requires-Dist: requests~=2.32.3
Dynamic: description
Dynamic: home-page
Dynamic: license
Dynamic: license-file
Dynamic: requires-dist
Dynamic: summary
